timberlogs/__init__.py
timberlogs/client.py
timberlogs/py.typed
timberlogs/types.py
timberlogs_client-1.0.0.dist-info/METADATA
timberlogs_client-1.0.0.dist-info/WHEEL
timberlogs_client-1.0.0.dist-info/licenses/LICENSE
timberlogs_client-1.0.0.dist-info/RECORD
