Metadata-Version: 2.4
Name: timberlogs-client
Version: 1.0.0
Summary: Official Timberlogs SDK for Python - structured logging made simple
Project-URL: Homepage, https://timberlogs.dev
Project-URL: Documentation, https://docs.timberlogs.dev
Project-URL: Repository, https://github.com/enaboapps/timberlogs-python-sdk
Project-URL: Issues, https://github.com/enaboapps/timberlogs-python-sdk/issues
Author-email: Timberlogs <timberlogs@proton.me>
License-Expression: MIT
License-File: LICENSE
Keywords: logging,observability,structured-logging,timberlogs
Classifier: Development Status :: 5 - Production/Stable
Classifier: Intended Audience :: Developers
Classifier: License :: OSI Approved :: MIT License
Classifier: Operating System :: OS Independent
Classifier: Programming Language :: Python :: 3
Classifier: Programming Language :: Python :: 3.8
Classifier: Programming Language :: Python :: 3.9
Classifier: Programming Language :: Python :: 3.10
Classifier: Programming Language :: Python :: 3.11
Classifier: Programming Language :: Python :: 3.12
Classifier: Topic :: System :: Logging
Classifier: Typing :: Typed
Requires-Python: >=3.8
Requires-Dist: httpx>=0.24.0
Provides-Extra: dev
Requires-Dist: mypy>=1.0.0; extra == 'dev'
Requires-Dist: pytest-asyncio>=0.21.0; extra == 'dev'
Requires-Dist: pytest-httpx>=0.22.0; extra == 'dev'
Requires-Dist: pytest>=7.0.0; extra == 'dev'
Requires-Dist: ruff>=0.1.0; extra == 'dev'
